[
  {
    "title": "The Legend of the Basilisk",
    "age_group": 6,
    "translations": [
      {
        "language": "English",
        "text": "Have you ever heard whispers carried on the wind?  Sometimes, these whispers tell amazing stories, stories that have been passed down through generations, like a secret treasure.  Let me tell you a whisper from the tall, snowy mountains of Switzerland, a story about a creature called the Basilisk.\n\nLong, long ago, nestled beside a sparkling lake, was a cozy little town.  The houses were like gingerbread houses, with pointy roofs and window boxes bursting with colorful flowers.  Children laughed as they chased butterflies in sunny meadows, and the smell of freshly baked bread drifted from every home.  It was a happy place, until… things started to go wrong.\n\nFirst, the flowers in the meadows began to droop and turn brown, even with sunshine and rain. Then, the butterflies stopped fluttering, and the birds stopped singing their cheerful songs.  A strange, cold shadow seemed to fall over the town, making everyone feel a little bit scared.\n\nOld Granny Willow, who knew all the stories and secrets of the town, shook her head sadly. “Oh dear, oh dear,” she mumbled, “It’s the Basilisk!”\n\n“The Basilisk?” asked a little boy named Timmy, his eyes wide as saucers. “What’s a Basilisk?”\n\nGranny Willow explained in a hushed voice, “A Basilisk is a very strange and scary creature.  They say it’s hatched from a rooster’s egg, and it has a look that can turn anything to stone!  If you even glance at it, you’ll freeze like a statue!”\n\nThe townspeople were terrified! They peeked nervously from their windows, afraid to go outside.  They whispered about the Basilisk hiding in the old, dark well at the edge of town.  No one dared to go near the well anymore.  The happy town was now quiet and gloomy.\n\nBut not everyone was ready to give up.  A brave young girl named Lily, who loved to climb trees and wasn’t afraid of spiders, decided she wouldn’t let a scary creature ruin her town.  Lily was clever, and she started to think.  “If the Basilisk’s look is so dangerous,” she thought, tapping her chin, “then maybe… maybe I can use that against it!”\n\nLily remembered seeing her reflection in a shiny pot in her kitchen.  “Aha!” she exclaimed. “A mirror!” If she could show the Basilisk its own look, maybe… just maybe… it would be turned to stone by its own scary gaze!\n\nLily found a big, round mirror from her grandma’s attic. It was dusty and old, but when she polished it, it shone like silver!  Early the next morning, when the sky was just turning pink, Lily bravely walked towards the old well. Her heart thumped like a drum in her chest, but she kept going.\n\nShe held the mirror out in front of her, facing away from herself and towards the well.  She crept closer and closer, her eyes fixed on the mirror’s reflection.  She could see the well in the mirror, dark and deep.\n\nSuddenly, in the mirror, she saw something move!  Two glowing, yellow eyes appeared in the darkness of the well.  It was the Basilisk!  It was even scarier than she had imagined, with scales like bumpy stones and a long, slithery tail.\n\nLily held her breath and stood perfectly still.  The Basilisk hissed, a sound like dry leaves rustling in the wind.  It stared right at the mirror, right at its own reflection!\n\nAnd then… *POOF!*  There was a flash of light, a puff of smoke, and the Basilisk was gone!  The reflection in the mirror showed only the dark well again.\n\nLily waited, holding her breath.  Silence.  She slowly lowered the mirror and peeked over the edge of the well.  It was empty!  The Basilisk was truly gone!\n\nLily ran back to town as fast as her legs could carry her, shouting, “It’s gone! The Basilisk is gone! I did it!”\n\nAt first, the townspeople were scared to believe her.  But then, they saw the sunshine getting brighter, the flowers slowly starting to perk up, and they heard a little bird chirp a happy tune.  They rushed to the well, and saw it was empty and safe.\n\nEveryone cheered and danced! They lifted Lily onto their shoulders and paraded her through the town.  The children started chasing butterflies again, and the smell of baking bread filled the air once more.  The happy town was happy again, all thanks to brave and clever Lily and her shiny mirror.\n\nAnd that, my friend, is the legend of the Basilisk, a whispered story from the Swiss mountains, reminding us that even the scariest monsters can be defeated with courage and a little bit of clever thinking.  And maybe, just maybe, if you listen very carefully on a windy day, you can still hear the whispers of this amazing tale."
      },
      {
        "language": "Chinese",
        "text": "你有没有听见过风儿带来的悄悄话呀？ 有时候，风中的悄悄话会讲一些很神奇的故事，就像秘密宝藏一样，一代代传下来。 今天，我就要告诉你一个从高高的、白雪皑皑的瑞士山上传来的悄悄话，一个关于名叫“蛇怪”的可怕生物的故事。\n\n很久很久以前，在一个闪闪发光的小湖边，有一个温暖又舒适的小镇。  那里的房子就像姜饼小屋一样，有着尖尖的屋顶，窗台上开满了五颜六色的鲜花。  孩子们在阳光明媚的草地上追逐蝴蝶，到处都飘着香喷喷的面包味儿。 那真是个快乐的地方，直到…… 一些糟糕的事情发生了。\n\n首先，草地上的花儿开始耷拉下脑袋，慢慢变黄变枯，即使有阳光和雨水也没用。 然后，蝴蝶不再飞舞，小鸟也不再唱它们欢快的歌儿了。  一种奇怪的、冰冷的阴影好像笼罩着小镇，让每个人都觉得有点害怕。\n\n柳树奶奶是一位老人家，她知道镇上所有的故事和秘密。 她伤心地摇了摇头， “哎呀，哎呀，” 她嘟囔着，“是蛇怪来了！”\n\n“蛇怪？”  一个小男孩提米睁大了眼睛，像两个小盘子一样圆。“蛇怪是什么呀？”  柳树奶奶用低低的声音解释说，“蛇怪是一种非常奇怪又可怕的生物。 人们说它是从公鸡下的蛋里孵出来的，它的眼睛有一种魔力，看一眼就能把所有东西变成石头！ 如果你只是看它一眼，就会像雕像一样僵住！”\n\n镇上的人们都吓坏了！ 他们紧张地从窗户后面偷偷往外看，害怕出门。 他们小声地议论着蛇怪就藏在镇子边上那口又旧又黑的井里。 再也没有人敢靠近那口井了。  原本快乐的小镇变得安静又阴沉。\n\n但是，并不是所有人都准备放弃。  一个勇敢的小女孩，名叫莉莉，她喜欢爬树，也不怕蜘蛛。 她决定不能让一个可怕的怪物毁掉自己的家乡。 莉莉很聪明，她开始动脑筋。“如果蛇怪的眼神这么危险，” 她一边想着，一边用手指轻轻敲着下巴，“那也许…… 也许我可以利用这一点来对付它！”\n\n莉莉想起了在厨房里，她曾在亮晶晶的锅子里看到自己的影子。“啊哈！”她兴奋地叫起来。“镜子！” 如果她能让蛇怪看到它自己的样子，也许…… 也许…… 它会被自己可怕的眼神变成石头！\n\n莉莉从奶奶家的阁楼里找到了一面又大又圆的镜子。 镜子上落满了灰尘，又旧又脏，但是当她把它擦干净后，镜子闪闪发光，像银子一样！ 第二天一大早，天空刚刚变成粉红色的时候，莉莉勇敢地走向那口旧井。 她的心怦怦直跳，像打鼓一样，但她还是继续向前走。\n\n她把镜子举在身前，镜面朝外，对着那口井。 她小心翼翼地，一步一步地靠近，眼睛紧紧地盯着镜子里的反射。 她在镜子里看到了那口井，又黑又深。\n\n突然，在镜子里，她看到有什么东西在动！ 两只发着黄色光芒的眼睛出现在井里的黑暗中。 是蛇怪！ 它比她想象的还要可怕，身上长着像凹凸不平的石头一样的鳞片，还有一条长长的、滑溜溜的尾巴。\n\n莉莉屏住呼吸，一动不动地站着。 蛇怪发出嘶嘶的声音，像风吹过干枯的树叶一样。 它直勾勾地盯着镜子，盯着镜子里自己的样子！\n\n然后…… “砰！”  一道闪光，一团烟雾，蛇怪不见了！ 镜子里又只剩下黑乎乎的井口。\n\n莉莉等待着，屏住呼吸。  一片寂静。 她慢慢放下镜子，小心地探头往井里看。  井里空空的！ 蛇怪真的消失了！\n\n莉莉飞快地跑回镇子，一边跑一边大声喊着：“不见了！蛇怪不见了！我成功了！”  一开始，镇上的人们都不敢相信她。  但是，他们看到阳光变得越来越明媚，花儿也慢慢抬起了头，他们还听到小鸟唱起了快乐的歌儿。 他们赶紧跑到井边，看到井里空空的，很安全。\n\n大家都欢呼雀跃，跳起舞来！ 他们把莉莉高高举起，放在肩膀上，抬着她在镇子里游行。  孩子们又开始追逐蝴蝶，香喷喷的面包味再次飘满了空气。  快乐的小镇又变得快乐起来，这都要感谢勇敢又聪明的莉莉和她那面亮晶晶的镜子。\n\n朋友，这就是关于蛇怪的传说，一个从瑞士山上传来的悄悄话故事。 它告诉我们，即使是最可怕的怪物，只要有勇气和一点点聪明的想法，也能够被战胜。  也许，也许，在刮风的日子里，如果你仔细听，还能听到这个神奇故事的悄悄话呢。"
      },
      {
        "language": "French",
        "text": "As-tu déjà entendu les secrets que le vent nous chuchote ?  Parfois, ces chuchotements racontent des histoires merveilleuses, des histoires transmises de génération en génération, comme un trésor caché. Laisse-moi te raconter un secret venu des hautes montagnes enneigées de Suisse, l'histoire d'une étrange créature appelée le Basilic.\n\nIl y a très longtemps, au bord d'un lac brillant comme un miroir, se cachait un joli petit village. Les maisons ressemblaient à des maisons de pain d'épices, avec des toits pointus et des fenêtres décorées de fleurs de toutes les couleurs. Les enfants riaient en courant après les papillons dans les champs ensoleillés, et une douce odeur de pain chaud s'échappait de chaque maison. C'était un endroit joyeux, jusqu'au jour où…  tout a commencé à changer.\n\nD'abord, les fleurs des champs ont commencé à pencher la tête et à devenir marron, même avec le soleil et la pluie.  Ensuite, les papillons ont arrêté de voler, et les oiseaux ne chantaient plus leurs jolies chansons.  Une ombre étrange et froide semblait recouvrir le village, et tout le monde avait un peu peur.\n\nLa vieille grand-mère Willow, qui connaissait toutes les histoires et tous les secrets du village, secoua la tête, tristement.  \"Oh là là, oh là là,\" murmura-t-elle, \"C'est le Basilic !\"\n\n\"Le Basilic ?\" demanda un petit garçon appelé Timmy, avec de grands yeux ronds. \"C'est quoi, un Basilic ?\"\n\nGrand-mère Willow expliqua à voix basse : \"Le Basilic, c'est une créature très bizarre et très méchante. On raconte qu'il sort d'un œuf de coq, et son regard peut changer n'importe quoi en pierre !  Si tu le regardes juste un instant, tu deviens dur comme une statue !\"\n\nLes habitants du village étaient ужасно effrayés ! Ils regardaient en cachette par les fenêtres, trop peur de sortir. Ils chuchotaient que le Basilic se cachait dans le vieux puits noir, tout au bout du village. Plus personne n'osait aller près du puits.  Le village joyeux était devenu silencieux et triste.\n\nMais tout le monde n'avait pas envie d'abandonner.  Une jeune fille courageuse, qui s'appelait Lily, adorait grimper aux arbres et n'avait pas peur des araignées. Elle décida qu'elle ne laisserait pas une créature méchante gâcher son village. Lily était très maligne, et elle se mit à réfléchir. \"Si le regard du Basilic est si dangereux,\" pensa-t-elle en se touchant le menton, \"alors… alors peut-être que je peux utiliser ça contre lui !\"\n\nLily se rappela avoir vu son image dans une casserole brillante dans la cuisine. \"Eurêka !\" s'écria-t-elle. \"Un miroir !\"  Si elle montrait au Basilic son propre reflet, peut-être... peut-être bien... qu'il se changerait lui-même en pierre avec son regard terrible !\n\nLily trouva un grand miroir rond dans le grenier de sa grand-mère. Il était couvert de poussière et un peu vieux, mais quand elle l'a frotté, il s'est mis à briller comme de l'argent !  Tôt le lendemain matin, quand le ciel devenait rose comme une pêche, Lily se dirigea courageusement vers le vieux puits. Son cœur battait très fort dans sa poitrine, comme un tambour, mais elle continuait d'avancer.\n\nElle tenait le miroir devant elle, face au puits, mais sans se regarder dedans.  Elle avançait doucement, tout doucement, les yeux fixés sur l'image dans le miroir. Elle voyait le puits dans le miroir, noir et profond.\n\nSoudain, dans le miroir, elle vit quelque chose bouger !  Deux yeux jaunes et brillants apparurent dans le noir du puits. C'était le Basilic ! Il était encore plus ужасный que dans ses cauchemars, avec des écailles comme des cailloux tout ronds et une longue queue qui serpentait.\n\nLily bloqua sa respiration et resta बिल्कुल immobile. Le Basilic se mit à siffler, un bruit comme des feuilles sèches qui craquent sous le vent. Il fixait le miroir, il regardait son propre visage !\n\nEt alors… *POUF !*  Un éclair de lumière, un nuage de fumée, et le Basilic avait disparu !  Dans le miroir, on ne voyait plus que le puits noir, tout simple.\n\nLily attendit, le souffle coupé.  Silence complet.  Doucement, elle baissa le miroir et regarda par-dessus le bord du puits.  Vide !  Le Basilic avait vraiment disparu !\n\nLily retourna au village en courant aussi vite qu'elle pouvait, en criant : \"Il est parti ! Le Basilic est parti ! C'est moi qui ai gagné !\"\n\nAu début, les habitants du village avaient du mal à la croire.  Mais après, ils ont vu le soleil briller plus fort, les fleurs relever doucement la tête, et ils ont entendu un petit oiseau chanter une chanson joyeuse. Alors, ils ont couru jusqu'au puits, et ils ont vu qu'il était vide et sans danger.\n\nTout le monde s'est mis à crier de joie et à danser ! Ils ont porté Lily sur leurs épaules et l'ont promenée dans tout le village en fête.  Les enfants se sont remis à courir après les papillons, et la bonne odeur de pain chaud a rempli l'air à nouveau.  Le village joyeux était redevenu joyeux, grâce à la courageuse et maligne Lily et à son miroir brillant.\n\nEt voilà, mon ami, c'est la légende du Basilic, une histoire chuchotée des montagnes de Suisse. Elle nous montre que même les monstres les plus ужасный peuvent être vaincus avec du courage et un peu d'intelligence. Et peut-être, si tu tends bien l'oreille un jour de grand vent, tu entendras toi aussi les chuchotements de cette histoire merveilleuse."
      },
      {
        "language": "German",
        "text": "Hast du jemals Flüstern im Wind gehört? Manchmal erzählen diese Flüstern ganz wunderbare Geschichten, Geschichten, die schon seit vielen Generationen weitergegeben werden, wie ein geheimer Schatz.  Ich möchte dir jetzt ein Flüstern aus den hohen, schneebedeckten Bergen der Schweiz erzählen, eine Geschichte über ein Wesen, das Basilisk genannt wird.\n\nVor langer, langer Zeit, eingebettet an einem glitzernden See, lag ein gemütliches kleines Städtchen. Die Häuser waren wie Lebkuchenhäuser, mit spitzen Dächern und Fensterkästen voller bunter Blumen. Kinder lachten, während sie Schmetterlinge auf sonnigen Wiesen jagten, und der Duft von frisch gebackenem Brot zog durch jedes Haus. Es war ein fröhlicher Ort, bis… etwas Schlimmes passierte.\n\nZuerst ließen die Blumen auf den Wiesen die Köpfe hängen und wurden braun, obwohl die Sonne schien und es regnete. Dann hörten die Schmetterlinge auf zu flattern und die Vögel zu zwitschern. Ein seltsamer, kalter Schatten schien über die Stadt zu fallen und machte allen ein bisschen Angst.\n\nDie alte Oma Weide, die alle Geschichten und Geheimnisse der Stadt kannte, schüttelte traurig den Kopf. „Oh je, oh je“, murmelte sie, „Es ist der Basilisk!“ „Der Basilisk?“, fragte ein kleiner Junge namens Timmy mit großen Augen. „Was ist ein Basilisk?“ Oma Weide erklärte mit leiser Stimme: „Ein Basilisk ist ein ganz seltsames und furchterregendes Wesen. Man sagt, er schlüpft aus einem Hahnen-Ei und sein Blick kann alles zu Stein verwandeln! Wenn du ihn nur ansiehst, erstarrst du wie eine Statue!“\n\nDie Stadtbewohner waren entsetzt! Sie lugten ängstlich aus ihren Fenstern und trauten sich nicht mehr nach draußen. Sie flüsterten über den Basilisk, der sich im alten, dunklen Brunnen am Stadtrand verstecken soll. Niemand wagte es mehr, in die Nähe des Brunnens zu gehen. Die fröhliche Stadt war jetzt still und trübselig.\n\nAber nicht alle wollten aufgeben. Ein mutiges junges Mädchen namens Lily, das gerne auf Bäume kletterte und keine Angst vor Spinnen hatte, beschloss, dass sie nicht zulassen würde, dass ein gruseliges Wesen ihre Stadt ruiniert. Lily war klug und begann nachzudenken. „Wenn der Blick des Basilisken so gefährlich ist“, dachte sie, während sie sich ans Kinn fasste, „dann kann ich das vielleicht… vielleicht gegen ihn verwenden!“\n\nLily erinnerte sich, ihr Spiegelbild in einem glänzenden Topf in ihrer Küche gesehen zu haben. „Aha!“, rief sie. „Ein Spiegel!“ Wenn sie dem Basilisk sein eigenes Spiegelbild zeigen könnte, würde er vielleicht… vielleicht… von seinem eigenen gruseligen Blick zu Stein verwandelt werden! Lily fand einen großen, runden Spiegel auf dem Dachboden ihrer Oma. Er war staubig und alt, aber als sie ihn polierte, glänzte er wie Silber! Früh am nächsten Morgen, als der Himmel gerade erst rosa wurde, ging Lily mutig zum alten Brunnen. Ihr Herz pochte wie eine Trommel in ihrer Brust, aber sie ging weiter.\n\nSie hielt den Spiegel vor sich, abgewandt von sich selbst und dem Brunnen zugewandt. Sie schlich näher und näher, ihre Augen auf das Spiegelbild im Spiegel gerichtet. Sie konnte den Brunnen im Spiegel sehen, dunkel und tief. Plötzlich sah sie im Spiegel etwas sich bewegen! Zwei leuchtende, gelbe Augen erschienen in der Dunkelheit des Brunnens. Es war der Basilisk! Er war noch furchterregender, als sie es sich vorgestellt hatte, mit Schuppen wie holprigen Steinen und einem langen, schleimigen Schwanz.\n\nLily hielt den Atem an und stand ganz still. Der Basilisk zischte, ein Geräusch wie trockene Blätter im Wind. Er starrte direkt in den Spiegel, direkt in sein eigenes Spiegelbild! Und dann… *PUFF!* Es gab einen Lichtblitz, eine Rauchwolke, und der Basilisk war verschwunden! Das Spiegelbild im Spiegel zeigte nur noch den dunklen Brunnen.\n\nLily wartete und hielt den Atem an. Stille. Langsam senkte sie den Spiegel und lugte über den Rand des Brunnens. Er war leer! Der Basilisk war wirklich weg! Lily rannte so schnell sie konnte zurück in die Stadt und rief: „Er ist weg! Der Basilisk ist weg! Ich habe es geschafft!“ Zuerst trauten sich die Stadtbewohner nicht, ihr zu glauben. Aber dann sahen sie, wie der Sonnenschein heller wurde, die Blumen langsam wieder aufblühten und sie hörten einen kleinen Vogel fröhlich zwitschern. Sie eilten zum Brunnen und sahen, dass er leer und sicher war. Alle jubelten und tanzten! Sie hoben Lily auf ihre Schultern und trugen sie durch die Stadt. Die Kinder jagten wieder Schmetterlinge und der Duft von Backbrot erfüllte wieder die Luft. Die fröhliche Stadt war wieder fröhlich, alles dank der mutigen und klugen Lily und ihrem glänzenden Spiegel.\n\nUnd das, mein Freund, ist die Legende vom Basilisk, eine geflüsterte Geschichte aus den Schweizer Bergen, die uns daran erinnert, dass selbst die gruseligsten Monster mit Mut und ein bisschen Klugheit besiegt werden können. Und vielleicht, ganz vielleicht, wenn du an einem windigen Tag ganz genau hinhörst, kannst du immer noch das Flüstern dieser wunderbaren Geschichte hören."
      }
    ]
  },
  {
    "title": "The Legend of the Devil’s Bridge",
    "age_group": 6,
    "translations": [
      {
        "language": "English",
        "text": "High up in the pointy mountains of Switzerland, where the air is crisp and the cows wear bells that go ‘ding-dong’, lived a small village.  The village was cozy, with wooden houses and flower boxes on every window. But there was a problem. A big, rushing, noisy river roared right through the valley, making it very hard for the villagers to visit their friends on the other side.\n\n“Oh, if only we had a bridge!” sighed little Mia, as she watched her grandpa try to cross the river on slippery stepping stones.  Splash! Grandpa’s foot slipped and he wobbled, but luckily he didn’t fall in.\n\nThe villagers had tried to build a bridge many times. They chopped down trees, they piled up stones, but the river was too strong and the gorge was too deep.  Every time they tried, the river would laugh and wash their bridge away like it was made of twigs.\n\nOne day, when everyone was feeling very glum about the river, a strange voice boomed from the mountains.  It sounded like rocks tumbling and thunder rumbling all at once.\n\n“Hahahaha! I hear your wishes!” the voice cackled.  Suddenly, a funny-looking creature appeared on the mountaintop. He had pointy ears, a long red nose, and eyes that sparkled like fireflies. He was the Devil! But not a scary scary devil, more of a mischievous, tricky devil.\n\n“I can build you a bridge!” the Devil shouted, his voice echoing through the valley. “A bridge so strong, it will never break!”\n\nThe villagers gasped. “Really?” they called back, their eyes wide with hope.\n\n“Yes, really!” said the Devil, twirling his pointy beard. “But… there’s a little price.” He winked a fiery wink. “For my hard work, I want the first soul to cross my bridge!”\n\nThe villagers mumbled amongst themselves.  A soul? That sounded a bit spooky.  But they really, really needed a bridge.  Finally, the Mayor, a wise old man with a long white beard, stepped forward.\n\n“Mr. Devil,” he said, “we accept your offer. Build us a bridge!”\n\nPoof! In a blink of an eye, with flashes of red smoke and the smell of burnt popcorn, a magnificent bridge appeared across the gorge! It was made of strong stones, stretching all the way to the other side.  The villagers had never seen anything so amazing.\n\n“Hahahaha!” roared the Devil, rubbing his hands together. “Now, who will be the first to cross?”\n\nThe villagers looked at each other nervously.  Nobody wanted to be the first ‘soul’.  Little Mia hid behind her grandma’s skirt.\n\nThen, the Mayor smiled. He had a clever idea! He whispered something to a young boy named Timmy. Timmy grinned and ran off to the village square.\n\nTimmy came back leading… a goat!  It was grumpy old Gertrude, the village goat, known for eating anything and everything.\n\nThe villagers chuckled.  They gently nudged Gertrude towards the bridge.  Gertrude, being a goat, was curious about everything. She sniffed the new bridge, wagged her little tail, and then CLOP CLOP CLOP, she walked right across!\n\n“BAAAAA!” Gertrude bleated happily from the other side.\n\nThe villagers cheered and clapped!  They had tricked the Devil!\n\nBut the Devil was NOT happy.  He stamped his foot so hard that the ground shook.  “A GOAT?! You tricked me with a silly goat!” he yelled, his face turning as red as his nose.\n\nThe Devil was so angry, he wanted to destroy the bridge he had just built. He picked up a HUGE rock, bigger than a house, and with all his might, he threw it at the bridge!  The villagers gasped, thinking their beautiful bridge was going to be smashed to pieces.\n\nBut just as the rock was about to hit the bridge, a brave little girl, it was Mia! stepped forward.  She remembered her grandma always said that crosses were strong against bad magic.  Quick as a wink, Mia picked up a piece of chalk from her pocket (she was always drawing!) and drew a big, bold cross on the rock, right before it landed.\n\nThe moment Mia drew the cross, *POOF!*  The Devil’s power vanished!  The rock stopped in mid-air, then tumbled harmlessly into the river with a *KERPLUNK!*  The Devil screamed a frustrated scream and disappeared in a puff of smoke, grumbling about silly goats and clever children.\n\nThe bridge stayed strong and sturdy, just as the Devil had promised.  From that day on, the villagers could easily visit their friends, trade goods, and Mia could visit her grandpa on the other side of the river whenever she wanted. They named it the Devil’s Bridge, to always remember the tricky Devil and the clever villagers who outsmarted him. And every time they crossed it, they remembered that even a little bit of cleverness and bravery can beat even the grumpiest, trickiest Devil. And sometimes, a grumpy goat can be a hero too!"
      },
      {
        "language": "Chinese",
        "text": "在瑞士高高的尖尖的山上，那里的空气又冷又新鲜，奶牛们戴着会发出“叮咚”声的铃铛。山脚下住着一个小村庄。村庄里很温暖舒适，家家户户都是木头房子，窗台上都摆满了花盒子。可是，村庄里有个难题。一条又大又急又吵闹的河流，正好穿过山谷，村民们去拜访住在河对岸的朋友，就变得非常困难。\n\n“哎，要是有座桥就好了！” 小女孩米娅叹着气说。她看着爷爷正踩着滑溜溜的石头，想要过河。 “扑通！” 爷爷的脚一滑，身体晃了晃，幸好没有掉进河里。\n\n村民们试过很多次要造一座桥。他们砍倒大树，堆起石头，可是河水太猛了，峡谷又太深了。每次他们尝试，河水都会哈哈大笑，把他们的桥冲走，就像桥是用小树枝搭起来的一样。\n\n有一天，大家都因为过不了河而闷闷不乐的时候，突然从山上传来一个奇怪的声音，轰隆隆的，听起来像是石头滚落和雷声一起响。\n\n“哈哈哈！我听到你们的愿望啦！” 那个声音尖声笑道。 突然，一个长相奇怪的家伙出现在山顶上。他长着尖尖的耳朵，红红的长鼻子，眼睛像萤火虫一样闪闪发光。 他是魔鬼！ 但不是那种可怕的魔鬼，更像是一个爱恶作剧、有点狡猾的魔鬼。\n\n“我可以给你们造一座桥！” 魔鬼喊道，他的声音在山谷里回荡。“一座非常坚固，永远不会坏的桥！”\n\n村民们倒吸一口凉气。“真的吗？” 他们大声问，眼睛里充满了希望。\n\n“真的真的！” 魔鬼说着，转了转他尖尖的胡子。“但是嘛……有一个小小的条件。” 他眨了眨火红的眼睛。“为了我的辛苦工作，我要第一个走过这座桥的灵魂！”\n\n村民们小声地嘀咕起来。 一个灵魂？ 这听起来有点吓人。 但是他们真的，真的需要一座桥。 最后，村长，一位留着长长白胡子的聪明老爷爷，站了出来。\n\n“魔鬼先生，” 他说，“我们接受你的提议。 请给我们造一座桥吧！”\n\n砰！ 眨眼间，红烟闪过，还带着一股爆米花的焦味，一座雄伟的桥梁就出现在峡谷上！ 桥是用坚固的石头砌成的，一直延伸到河对岸。 村民们从来没见过这么神奇的事情。\n\n“哈哈哈！” 魔鬼咆哮着，搓着双手。“现在，谁来做第一个过桥的人呢？”\n\n村民们紧张地互相看着。 谁也不想做第一个“灵魂”。 小米娅躲到奶奶的裙子后面。\n\n这时，村长笑了笑。 他想到了一个聪明的办法！ 他悄悄地对一个名叫提米的小男孩说了些什么。 提米咧嘴一笑，跑向村子的广场。\n\n提米回来的时候，牵着……一只山羊！ 是脾气暴躁的老格特鲁德，村子里出了名的什么都吃的山羊。\n\n村民们都咯咯地笑了起来。 他们轻轻地推着格特鲁德朝桥边走去。 格特鲁德，作为一只山羊，对什么都好奇。 她嗅了嗅新桥，摇了摇小尾巴，然后 “嗒嗒嗒”，她就走过桥了！\n\n“咩——！” 格特鲁德在对岸高兴地叫着。\n\n村民们欢呼雀跃，鼓起掌来！ 他们骗过了魔鬼！\n\n可是魔鬼一点儿也不高兴。 他气得跺了一下脚，地面都震动起来。“一只山羊？！ 你们竟然用一只傻山羊骗我！” 他大吼大叫，脸涨得像他的鼻子一样红。\n\n魔鬼太生气了，他想毁掉他刚刚建好的桥。 他抱起一块巨大的石头，比房子还大，用尽全身力气，朝桥扔去！ 村民们惊叫起来，以为他们美丽的桥梁就要被砸成碎片了。\n\n就在石头要砸到桥梁的时候，一个勇敢的小女孩，正是小米娅！站了出来。 她想起奶奶总是说，十字架可以抵抗坏魔法。 米娅眼疾手快，从口袋里掏出一支粉笔（她总是喜欢画画！），在石头落下来之前，在石头上画了一个又大又粗的十字架。\n\n就在米娅画出十字架的那一瞬间， “砰！” 魔鬼的力量消失了！ 石头停在半空中，然后无力地掉进河里，发出 “扑通” 一声！ 魔鬼发出了一声沮丧的尖叫，化作一缕烟消失了，嘴里还嘟囔着关于傻山羊和聪明孩子的话。\n\n桥梁依然坚固结实，就像魔鬼承诺的那样。 从那天起，村民们可以轻松地拜访朋友，交换货物，小米娅也可以随时去河对岸看望爷爷了。 他们把这座桥叫做“魔鬼桥”，为了永远记住狡猾的魔鬼和聪明地战胜了他的村民们。 每次走过这座桥，他们都会想起，即使是一点点聪明和勇敢，也能战胜最坏脾气、最狡猾的魔鬼。 而且有时候，一只坏脾气的山羊，也能成为英雄呢！"
      },
      {
        "language": "French",
        "text": "Tout en haut des montagnes pointues de Suisse, là où l'air est frais et les vaches portent des cloches qui font ‘drelin-drelin’, vivait un petit village. Le village était douillet, avec des maisons en bois et des boîtes à fleurs à chaque fenêtre. Mais il y avait un problème. Une grande rivière bruyante et agitée rugissait au milieu de la vallée, rendant très difficile pour les villageois de rendre visite à leurs amis de l'autre côté.\n\n“Oh, si seulement on avait un pont !” soupira la petite Mia, en regardant son grand-père essayer de traverser la rivière sur des pierres glissantes.  Plouf ! Le pied de grand-père a glissé et il a vacillé, mais heureusement, il n'est pas tombé.\n\nLes villageois avaient essayé de construire un pont plusieurs fois. Ils ont coupé des arbres, ils ont empilé des pierres, mais la rivière était trop forte et la gorge trop profonde. À chaque fois qu'ils essayaient, la rivière riait et emportait leur pont comme s'il était fait de brindilles.\n\nUn jour, alors que tout le monde était très triste à cause de la rivière, une voix étrange a grondé depuis les montagnes. On aurait dit des rochers qui dégringolent et le tonnerre qui gronde en même temps.\n\n“Hahahaha ! J'entends vos souhaits !” gloussa la voix. Soudain, une créature drôle est apparue au sommet de la montagne. Il avait des oreilles pointues, un long nez rouge et des yeux qui étincelaient comme des lucioles. C'était le Diable ! Mais pas un diable vraiment méchant, plutôt un diable farceur et rusé.\n\n“Je peux vous construire un pont !” cria le Diable, sa voix résonnant dans la vallée. “Un pont si solide qu'il ne cassera jamais !”\n\nLes villageois furent bouche bée. “Vraiment ?” répondirent-ils, les yeux remplis d'espoir.\n\n“Oui, vraiment !” dit le Diable en tortillant sa barbe pointue. “Mais… il y a un petit prix.” Il fit un clin d'œil de feu. “Pour mon dur labeur, je veux la première âme qui traversera mon pont !”\n\nLes villageois murmurèrent entre eux. Une âme ? Ça semblait un peu effrayant. Mais ils avaient vraiment, vraiment besoin d'un pont. Finalement, le Maire, un vieil homme sage avec une longue barbe blanche, s'avança.\n\n“Monsieur le Diable,” dit-il, “nous acceptons votre offre. Construisez-nous un pont !”\n\nPouff ! En un clin d'œil, avec des éclairs de fumée rouge et une odeur de pop-corn brûlé, un magnifique pont apparut au-dessus de la gorge ! Il était fait de pierres solides, s'étendant jusqu'à l'autre côté. Les villageois n'avaient jamais rien vu d'aussi incroyable.\n\n“Hahahaha !” rugit le Diable en se frottant les mains. “Maintenant, qui sera le premier à traverser ?”\n\nLes villageois se regardèrent nerveusement. Personne ne voulait être la première ‘âme’. La petite Mia se cacha derrière la jupe de sa grand-mère.\n\nAlors, le Maire sourit. Il avait une idée maligne ! Il murmura quelque chose à un jeune garçon nommé Timmy. Timmy sourit et courut vers la place du village.\n\nTimmy revint en menant… une chèvre ! C'était Gertrude la grincheuse, la chèvre du village, connue pour manger tout et n'importe quoi.\n\nLes villageois rirent doucement. Ils poussèrent doucement Gertrude vers le pont. Gertrude, étant une chèvre, était curieuse de tout. Elle renifla le nouveau pont, remua sa petite queue, et puis CLOP CLOP CLOP, elle traversa le pont !\n\n“BÊÊÊÊ !” bêla joyeusement Gertrude de l'autre côté.\n\nLes villageois applaudirent et crièrent de joie ! Ils avaient piégé le Diable !\n\nMais le Diable n'était PAS content. Il tapa du pied si fort que le sol trembla. “UNE CHÈVRE ?! Vous m'avez piégé avec une chèvre stupide !” hurla-t-il, son visage devenant rouge comme son nez.\n\nLe Diable était si en colère qu'il voulait détruire le pont qu'il venait de construire. Il ramassa un ÉNORME rocher, plus gros qu'une maison, et de toutes ses forces, il le lança sur le pont ! Les villageois haletèrent, pensant que leur beau pont allait être réduit en miettes.\n\nMais juste au moment où le rocher allait frapper le pont, une petite fille courageuse, c'était Mia ! s'avança. Elle se souvenait que sa grand-mère disait toujours que les croix étaient fortes contre la mauvaise magie. Rapide comme l'éclair, Mia sortit un morceau de craie de sa poche (elle dessinait toujours !) et dessina une grande et belle croix sur le rocher, juste avant qu'il n'atterrisse.\n\nAu moment où Mia dessina la croix, *POUFFF !* Le pouvoir du Diable disparut ! Le rocher s'arrêta en plein air, puis dégringola inoffensivement dans la rivière avec un *PLOUF !* Le Diable poussa un cri de frustration et disparut dans un nuage de fumée, en grommelant à propos des chèvres stupides et des enfants intelligents.\n\nLe pont resta solide et robuste, comme le Diable l'avait promis. À partir de ce jour, les villageois purent facilement rendre visite à leurs amis, échanger des marchandises, et Mia pouvait rendre visite à son grand-père de l'autre côté de la rivière quand elle le voulait. Ils l'ont appelé le Pont du Diable, pour toujours se souvenir du Diable rusé et des villageois intelligents qui l'ont déjoué. Et chaque fois qu'ils le traversaient, ils se souvenaient que même un peu d'intelligence et de courage peuvent vaincre même le Diable le plus grincheux et le plus rusé. Et parfois, une chèvre grincheuse peut aussi être un héros !"
      },
      {
        "language": "German",
        "text": "Ganz oben in den spitzen Bergen der Schweiz, wo die Luft klar und frisch ist und die Kühe Glöckchen tragen, die \"bim-bam\" machen, lag ein kleines Dorf. Das Dorf war gemütlich, mit Holzhäusern und Blumenkästen an jedem Fenster. Aber es gab ein Problem. Mitten durch das Tal rauschte ein großer, lauter Fluss. Er war so wild, dass es für die Dorfbewohner sehr schwer war, ihre Freunde auf der anderen Seite zu besuchen.\n\n\"Ach, hätten wir doch eine Brücke!\", seufzte die kleine Mia, als sie zusah, wie ihr Opa versuchte, den Fluss über rutschige Trittsteine zu überqueren. Platsch! Opas Fuß rutschte ab und er wackelte, aber zum Glück fiel er nicht hinein.\n\nDie Dorfbewohner hatten viele Male versucht, eine Brücke zu bauen. Sie fällten Bäume, sie stapelten Steine, aber der Fluss war zu stark und die Schlucht war zu tief. Jedes Mal, wenn sie es versuchten, lachte der Fluss und spülte ihre Brücke weg, als wäre sie aus Zweigen gemacht.\n\nEines Tages, als alle sehr traurig wegen des Flusses waren, dröhnte eine seltsame Stimme aus den Bergen. Es klang wie fallende Felsen und rollender Donner auf einmal.\n\n\"Hahahaha! Ich höre eure Wünsche!\", gackerte die Stimme. Plötzlich erschien ein komisch aussehendes Wesen auf dem Berggipfel. Er hatte spitze Ohren, eine lange rote Nase und Augen, die wie Glühwürmchen funkelten. Er war der Teufel! Aber kein gruseliger Teufel, eher ein schelmischer, trickreicher Teufel.\n\n\"Ich kann euch eine Brücke bauen!\", rief der Teufel, seine Stimme hallte durch das Tal. \"Eine Brücke so stark, dass sie niemals kaputt gehen wird!\"\n\nDie Dorfbewohner keuchten. \"Wirklich?\", riefen sie zurück, ihre Augen voller Hoffnung.\n\n\"Ja, wirklich!\", sagte der Teufel und zwirbelte seinen spitzen Bart. \"Aber... es gibt einen kleinen Preis.\" Er zwinkerte mit einem feurigen Zwinkern. \"Für meine harte Arbeit will ich die erste Seele, die meine Brücke überquert!\"\n\nDie Dorfbewohner murmelten untereinander. Eine Seele? Das klang ein bisschen gruselig. Aber sie brauchten wirklich, wirklich eine Brücke. Schließlich trat der Bürgermeister vor, ein weiser alter Mann mit einem langen weißen Bart.\n\n\"Herr Teufel\", sagte er, \"wir nehmen Ihr Angebot an. Bauen Sie uns eine Brücke!\"\n\nSchwuppdiwupp! Im Handumdrehen, mit roten Rauchwolken und dem Geruch von verbranntem Popcorn, erschien eine prächtige Brücke über die Schlucht! Sie war aus starken Steinen gebaut und reichte bis zur anderen Seite. Die Dorfbewohner hatten noch nie etwas so Tolles gesehen.\n\n\"Hahahaha!\", brüllte der Teufel und rieb sich die Hände. \"Na, wer wird der Erste sein, der hinübergeht?\"\n\nDie Dorfbewohner sahen sich nervös an. Niemand wollte die erste 'Seele' sein. Die kleine Mia versteckte sich hinter dem Rock ihrer Oma.\n\nDa lächelte der Bürgermeister. Er hatte eine schlaue Idee! Er flüsterte einem kleinen Jungen namens Timmy etwas ins Ohr. Timmy grinste und rannte zum Dorfplatz.\n\nTimmy kam zurück und führte... eine Ziege! Es war die mürrische alte Gertrude, die Dorfziege, die dafür bekannt war, alles und jedes zu fressen.\n\nDie Dorfbewohner kicherten. Sie stupsten Gertrude sanft in Richtung der Brücke. Gertrude war als Ziege neugierig auf alles. Sie beschnupperte die neue Brücke, wedelte mit ihrem kleinen Schwanz und dann KLOPP KLOPP KLOPP, spazierte sie direkt hinüber!\n\n\"MÄÄÄÄÄH!\", meckerte Gertrude fröhlich von der anderen Seite.\n\nDie Dorfbewohner jubelten und klatschten! Sie hatten den Teufel ausgetrickst!\n\nAber der Teufel war NICHT glücklich. Er stampfte so fest mit dem Fuß auf, dass die Erde bebte. \"EINE ZIEGE?! Ihr habt mich mit einer dummen Ziege ausgetrickst!\", brüllte er, sein Gesicht wurde so rot wie seine Nase.\n\nDer Teufel war so wütend, dass er die Brücke zerstören wollte, die er gerade gebaut hatte. Er hob einen RIESIGEN Stein auf, größer als ein Haus, und warf ihn mit aller Kraft auf die Brücke!\n\nDie Dorfbewohner keuchten, weil sie dachten, ihre schöne Brücke würde in Stücke zerschlagen werden.\n\nAber gerade als der Stein die Brücke treffen sollte, trat ein mutiges kleines Mädchen vor, es war Mia! Sie erinnerte sich daran, dass ihre Oma immer gesagt hatte, dass Kreuze stark gegen böse Zauberei sind. Blitzschnell zog Mia ein Stück Kreide aus ihrer Tasche (sie malte immer gern!) und malte ein großes, dickes Kreuz auf den Stein, kurz bevor er landete.\n\nIn dem Moment, als Mia das Kreuz malte, *PUFF!* Verschwand die Macht des Teufels! Der Stein blieb in der Luft stehen und plumpste dann harmlos mit einem *PLUMPS!* in den Fluss. Der Teufel schrie einen wütenden Schrei und verschwand in einer Rauchwolke, während er über dumme Ziegen und schlaue Kinder schimpfte.\n\nDie Brücke blieb stark und fest, genau wie der Teufel versprochen hatte. Von diesem Tag an konnten die Dorfbewohner ihre Freunde einfach besuchen, Waren tauschen und Mia konnte ihren Opa besuchen, wann immer sie wollte. Sie nannten sie die Teufelsbrücke, um sich immer an den trickreichen Teufel und die schlauen Dorfbewohner zu erinnern, die ihn überlistet hatten. Und jedes Mal, wenn sie sie überquerten, erinnerten sie sich daran, dass ein bisschen Klugheit und Mut selbst den mürrischsten und trickreichsten Teufel besiegen können. Und manchmal kann auch eine mürrische Ziege ein Held sein!"
      }
    ]
  }
]